{
  "@context": {
   "@vocab": "http://schema.org/"
 },
 "@type": "Article",
 "@id": "http://intro2libsys.info/Article/2011-shift-index",
 "author": [
    {
     "@id": "http://intro2libsys.info/Person/hagel-john" 
    },
    {
     "@id": "http://intro2libsys.info/Person/brown-john-seely"
    },
    { 
     "@id": "http://intro2libsys.info/Person/kulasooriya-duleesha"   
    }
 ],
 "copyrightYear": 2011,
 "headline": "The 2011 Shift Index: Measuring the forces of long-term change",
 "keywords": [], 
 "name": "The 2011 Shift Index",
 "publisher": {
   "@id": "http://intro2libsys.info/Organization/deloitte-center-for-the-edge"
 },
 "thumbnailUrl": "2011-shift-index-thumbnail.png",
 "url": "http://www.deloitte.com/assets/Dcom-UnitedStates/Local%20Assets/Documents/TMT_us_tmt/us_tmt_shiftindex_revised_120512.pdf"
}
