{
  "@context": {
    "@vocab": "http://schema.org/", 
    "bf": "http://bibframe.org/vocab/"
  }, 
  "@id": "http://intro2libsys.info/Person/salo-dorothea", 
  "@type": "Person", 
  "bf:adminInfo": {
    "bf:creationDate": "2013-12-18T18:42:36.220000", 
    "bf:descriptionConventions": "Using schema.org for descriptive metadata", 
    "bf:descriptionLanguage": "English"
  }, 
  "familyName": "Salo", 
  "givenName": "Dorothea", 
  "name": "Dorothea Salo", 
  "url": "http://intro2libsys.info/Person/DorotheaSalo"
}
